{
  "date": "2026-07-06",
  "generated": "2026-07-06T09:20:04-04:00",
  "probs_asof": "2026-06-30",
  "surge_pct": 0.3,
  "fwd_days": 10,
  "base": {
    "p_up": 0.0564,
    "p_down": 0.02,
    "n": 165847
  },
  "cap_band": [
    100000000.0,
    2000000000.0
  ],
  "setups": [
    {
      "cash_runway_months": 7.7,
      "dilution_risk": false,
      "symbol": "RGNX",
      "name": "REGENXBIO Inc.",
      "price": 13.28,
      "heat": 0.71,
      "setup": 0.23,
      "near_high": 0.82,
      "extended": false,
      "pos_in_range": 1.0,
      "tightness": 0.938,
      "market_cap": 686544393.0752459,
      "in_band": true,
      "dollar_vol": 24561464.0,
      "liquid": true,
      "short_pct": 0.1928,
      "bucket_label": "+10%/5d",
      "p_up": 0.0911,
      "p_down": 0.0318,
      "why": "+30% 5d, 19% short",
      "days_to_catalyst": 53,
      "nearest_phase": "PHASE2,PHASE3",
      "exit_by": "2026-08-21",
      "cat_quality": "phase2",
      "platform": true,
      "catalysts": [
        {
          "date": "2026-08",
          "phase": "PHASE2,PHASE3",
          "title": "AFFINITY DUCHENNE: RGX-202 Gene Therapy in Par"
        },
        {
          "date": "2028-04-30",
          "phase": "PHASE3",
          "title": "RGX-121-3102 Gene Therapy in Participants With"
        }
      ],
      "insider_buys": 0,
      "insider_usd": 0,
      "insider_recent": null,
      "conviction": "MED",
      "stop": 9.96,
      "trail_pct": 28,
      "structure": "RUN-UP PLAY (Phase 2 efficacy ~53d = the sweet spot) - buy the run-up, TARGET EXIT ~2026-08-21 (~1wk BEFORE data); don't hold the binary."
    },
    {
      "cash_runway_months": 43.5,
      "dilution_risk": false,
      "symbol": "IRON",
      "name": "Disc Medicine, Inc.",
      "price": 76.26,
      "heat": 0.55,
      "setup": 0.86,
      "near_high": 0.909,
      "extended": false,
      "pos_in_range": 1.0,
      "tightness": 0.175,
      "market_cap": 2913062608.742058,
      "in_band": false,
      "dollar_vol": 56547956.0,
      "liquid": true,
      "short_pct": 0.18360001,
      "bucket_label": "vol>=1.5x & +5%/5d",
      "p_up": 0.1034,
      "p_down": 0.0332,
      "why": "vol building 1.6x, coiled near range-top, +9% 5d, 18% short",
      "days_to_catalyst": 84,
      "nearest_phase": "PHASE1,PHASE2",
      "exit_by": "2026-09-21",
      "cat_quality": "phase2",
      "platform": false,
      "catalysts": [
        {
          "date": "2026-09",
          "phase": "PHASE1,PHASE2",
          "title": "Study of DISC-0974 (RALLY-MF) in Participants "
        },
        {
          "date": "2026-09",
          "phase": "PHASE3",
          "title": "Study of Bitopertin in Participants With EPP o"
        },
        {
          "date": "2026-10",
          "phase": "PHASE2",
          "title": "Study of DISC-0974-201 in Participants With IB"
        }
      ],
      "insider_buys": 0,
      "insider_usd": 0,
      "insider_recent": null,
      "conviction": "MED",
      "stop": 57.2,
      "trail_pct": 28,
      "structure": "RUN-UP PLAY (Phase 2 efficacy ~84d = the sweet spot) - buy the run-up, TARGET EXIT ~2026-09-21 (~1wk BEFORE data); don't hold the binary."
    },
    {
      "cash_runway_months": 7.8,
      "dilution_risk": false,
      "symbol": "ACHV",
      "name": "Achieve Life Sciences, Inc.",
      "price": 6.4,
      "heat": 0.74,
      "setup": 0.57,
      "near_high": 0.9,
      "extended": false,
      "pos_in_range": 0.937,
      "tightness": 0.389,
      "market_cap": 657017974.5903306,
      "in_band": true,
      "dollar_vol": 15710917.0,
      "liquid": true,
      "short_pct": 0.0806,
      "bucket_label": "vol>=1.5x & +5%/5d",
      "p_up": 0.1034,
      "p_down": 0.0332,
      "why": "vol building 1.6x, coiled near range-top, +12% 5d, 8% short",
      "days_to_catalyst": 132,
      "nearest_phase": "PHASE3",
      "exit_by": null,
      "cat_quality": "phase3",
      "platform": false,
      "catalysts": [
        {
          "date": "2026-11-15",
          "phase": "PHASE3",
          "title": "Phase 3 Trial Evaluating the Efficacy and Safe"
        }
      ],
      "insider_buys": 0,
      "insider_usd": 0,
      "insider_recent": null,
      "conviction": "MED",
      "stop": 4.8,
      "trail_pct": 28,
      "structure": "Phase 3 ~132d - largely PRICED IN + binary gap-down risk if it misses. Not a clean run-up."
    },
    {
      "cash_runway_months": 40.9,
      "dilution_risk": false,
      "symbol": "ZBIO",
      "name": "Zenas BioPharma, Inc.",
      "price": 27.23,
      "heat": 0.84,
      "setup": 0.25,
      "near_high": 0.921,
      "extended": false,
      "pos_in_range": 0.931,
      "tightness": 0.556,
      "market_cap": 1719121826.8098335,
      "in_band": true,
      "dollar_vol": 24453365.0,
      "liquid": true,
      "short_pct": 0.2628,
      "bucket_label": "vol>=1.5x & +5%/5d",
      "p_up": 0.1034,
      "p_down": 0.0332,
      "why": "vol building 1.9x, +10% 5d, 26% short",
      "days_to_catalyst": null,
      "nearest_phase": null,
      "exit_by": null,
      "cat_quality": null,
      "platform": false,
      "catalysts": [
        {
          "date": "2030-06",
          "phase": "PHASE3",
          "title": "A Study of Orelabrutinib in Patients With Prim"
        },
        {
          "date": "2030-06",
          "phase": "PHASE3",
          "title": "A Study of Orelabrutinib in Patients With Seco"
        }
      ],
      "insider_buys": 3,
      "insider_usd": 2080000.0,
      "insider_recent": "2026-05-18",
      "conviction": "MED",
      "stop": 20.42,
      "trail_pct": 28,
      "structure": "no near-term Phase-2 catalyst - momentum/heat play only (higher uncertainty)."
    },
    {
      "cash_runway_months": 30.1,
      "dilution_risk": false,
      "symbol": "VRDN",
      "name": "Viridian Therapeutics, Inc.",
      "price": 19.4,
      "heat": 0.59,
      "setup": 0.87,
      "near_high": 0.566,
      "extended": false,
      "pos_in_range": 1.0,
      "tightness": 0.216,
      "market_cap": 2142296988.6751823,
      "in_band": false,
      "dollar_vol": 41862845.0,
      "liquid": true,
      "short_pct": 0.14109999,
      "bucket_label": "vol>=1.5x & +5%/5d",
      "p_up": 0.1034,
      "p_down": 0.0332,
      "why": "vol building 1.8x, coiled near range-top, +12% 5d, 14% short",
      "days_to_catalyst": null,
      "nearest_phase": null,
      "exit_by": null,
      "cat_quality": null,
      "platform": false,
      "catalysts": [],
      "insider_buys": 1,
      "insider_usd": 19999990.0,
      "insider_recent": "2026-05-13",
      "conviction": "MED",
      "stop": 14.55,
      "trail_pct": 28,
      "structure": "no near-term Phase-2 catalyst - momentum/heat play only (higher uncertainty)."
    },
    {
      "cash_runway_months": 52.5,
      "dilution_risk": false,
      "symbol": "RNA",
      "name": "Atrium Therapeutics, Inc.",
      "price": 13.65,
      "heat": 0.48,
      "setup": 0.85,
      "near_high": 0.814,
      "extended": false,
      "pos_in_range": 1.0,
      "tightness": 0.164,
      "market_cap": 233492020.42471504,
      "in_band": true,
      "dollar_vol": 3066888.0,
      "liquid": true,
      "short_pct": null,
      "bucket_label": "vol>=1.5x & +5%/5d",
      "p_up": 0.1034,
      "p_down": 0.0332,
      "why": "vol building 1.5x, coiled near range-top, +7% 5d",
      "days_to_catalyst": null,
      "nearest_phase": null,
      "exit_by": null,
      "cat_quality": null,
      "platform": false,
      "catalysts": [],
      "insider_buys": 0,
      "insider_usd": 0,
      "insider_recent": null,
      "conviction": "LOW",
      "stop": 10.24,
      "trail_pct": 28,
      "structure": "no near-term Phase-2 catalyst - momentum/heat play only (higher uncertainty)."
    },
    {
      "cash_runway_months": null,
      "dilution_risk": false,
      "symbol": "MDXG",
      "name": "MiMedx Group, Inc.",
      "price": 3.95,
      "heat": 0.36,
      "setup": 0.84,
      "near_high": 0.608,
      "extended": false,
      "pos_in_range": 1.0,
      "tightness": 0.117,
      "market_cap": 588335644.5522859,
      "in_band": true,
      "dollar_vol": 5000301.0,
      "liquid": true,
      "short_pct": 0.0651,
      "bucket_label": "baseline",
      "p_up": 0.0564,
      "p_down": 0.02,
      "why": "vol building 1.4x, coiled near range-top, +4% 5d, 7% short",
      "days_to_catalyst": null,
      "nearest_phase": null,
      "exit_by": null,
      "cat_quality": null,
      "platform": false,
      "catalysts": [],
      "insider_buys": 0,
      "insider_usd": 0,
      "insider_recent": null,
      "conviction": "LOW",
      "stop": 2.96,
      "trail_pct": 28,
      "structure": "no near-term Phase-2 catalyst - momentum/heat play only (higher uncertainty)."
    },
    {
      "cash_runway_months": 148.0,
      "dilution_risk": false,
      "symbol": "JANX",
      "name": "Janux Therapeutics, Inc.",
      "price": 15.54,
      "heat": 0.46,
      "setup": 0.76,
      "near_high": 0.936,
      "extended": false,
      "pos_in_range": 1.0,
      "tightness": 0.168,
      "market_cap": 947696858.8336315,
      "in_band": true,
      "dollar_vol": 20485282.0,
      "liquid": true,
      "short_pct": 0.16,
      "bucket_label": "baseline",
      "p_up": 0.0564,
      "p_down": 0.02,
      "why": "coiled near range-top, +7% 5d, 16% short",
      "days_to_catalyst": 25,
      "nearest_phase": "PHASE1",
      "exit_by": null,
      "cat_quality": "phase1_weak",
      "platform": false,
      "catalysts": [
        {
          "date": "2026-07-31",
          "phase": "PHASE1",
          "title": "Study of JANX008 in Subjects With Advanced or "
        },
        {
          "date": "2027-07",
          "phase": "PHASE1",
          "title": "Study of JANX007 in Subjects With Metastatic C"
        },
        {
          "date": "2028-05",
          "phase": "PHASE1",
          "title": "Study of JANX014 in Subjects With Metastatic C"
        }
      ],
      "insider_buys": 0,
      "insider_usd": 0,
      "insider_recent": null,
      "conviction": "LOW",
      "stop": 11.65,
      "trail_pct": 28,
      "structure": "Phase 1 only ~25d - SAFETY/dosage (~3% avg uplift). WEAK run-up - skip unless it's a platform play. NOT the Phase-2 efficacy setup."
    }
  ],
  "heat": [
    {
      "cash_runway_months": 45.6,
      "dilution_risk": false,
      "symbol": "SLS",
      "name": "SELLAS Life Sciences Group, Inc.",
      "price": 14.98,
      "heat": 0.93,
      "setup": 0.25,
      "near_high": 0.943,
      "extended": false,
      "pos_in_range": 0.955,
      "tightness": 1.232,
      "market_cap": 2945555868.508751,
      "in_band": false,
      "dollar_vol": 122021822.0,
      "liquid": true,
      "short_pct": 0.32349998,
      "bucket_label": "vol>=1.5x & +5%/5d",
      "p_up": 0.1034,
      "p_down": 0.0332,
      "why": "vol building 2.0x, +42% 5d, 32% short",
      "days_to_catalyst": null,
      "nearest_phase": null,
      "exit_by": null,
      "cat_quality": null,
      "platform": false,
      "catalysts": [
        {
          "date": "2026-12-30",
          "phase": "PHASE1,PHASE2",
          "title": "Study of SLS009 (Formerly GFH009) a Potent Hig"
        }
      ],
      "insider_buys": 0,
      "insider_usd": 0,
      "insider_recent": null,
      "conviction": "LOW",
      "stop": 11.23,
      "trail_pct": 28,
      "structure": "no near-term Phase-2 catalyst - momentum/heat play only (higher uncertainty)."
    },
    {
      "cash_runway_months": 39.4,
      "dilution_risk": false,
      "symbol": "VOR",
      "name": "Vor Biopharma Inc.",
      "price": 20.59,
      "heat": 0.9,
      "setup": 0.33,
      "near_high": 0.927,
      "extended": false,
      "pos_in_range": 1.0,
      "tightness": 0.5,
      "market_cap": 1115687215.6981087,
      "in_band": true,
      "dollar_vol": 26923341.0,
      "liquid": true,
      "short_pct": 0.1314,
      "bucket_label": "vol>=2x & +10%/5d",
      "p_up": 0.1546,
      "p_down": 0.0461,
      "why": "vol building 2.1x, +38% 5d, 13% short",
      "days_to_catalyst": null,
      "nearest_phase": null,
      "exit_by": null,
      "cat_quality": null,
      "platform": false,
      "catalysts": [
        {
          "date": "2027-05",
          "phase": "PHASE3",
          "title": "A Study of Telitacicept for the Treatment of G"
        },
        {
          "date": "2028-12",
          "phase": "PHASE3",
          "title": "Phase 3 Study of Telitacicept in Active Primar"
        }
      ],
      "insider_buys": 0,
      "insider_usd": 0,
      "insider_recent": null,
      "conviction": "LOW",
      "stop": 15.44,
      "trail_pct": 28,
      "structure": "no near-term Phase-2 catalyst - momentum/heat play only (higher uncertainty)."
    },
    {
      "cash_runway_months": 257.0,
      "dilution_risk": false,
      "symbol": "DMRA",
      "name": "Damora Therapeutics, Inc.",
      "price": 29.98,
      "heat": 0.85,
      "setup": 0.71,
      "near_high": 0.882,
      "extended": false,
      "pos_in_range": 1.0,
      "tightness": 0.42,
      "market_cap": 1845364727.943184,
      "in_band": true,
      "dollar_vol": 22273968.0,
      "liquid": true,
      "short_pct": 0.0249,
      "bucket_label": "vol>=2x & +10%/5d",
      "p_up": 0.1546,
      "p_down": 0.0461,
      "why": "vol building 2.4x, coiled near range-top, +33% 5d, 2% short",
      "days_to_catalyst": null,
      "nearest_phase": null,
      "exit_by": null,
      "cat_quality": null,
      "platform": false,
      "catalysts": [],
      "insider_buys": 0,
      "insider_usd": 0,
      "insider_recent": null,
      "conviction": "LOW",
      "stop": 22.48,
      "trail_pct": 28,
      "structure": "no near-term Phase-2 catalyst - momentum/heat play only (higher uncertainty)."
    },
    {
      "cash_runway_months": 10.0,
      "dilution_risk": false,
      "symbol": "RARE",
      "name": "Ultragenyx Pharmaceutical Inc.",
      "price": 33.47,
      "heat": 0.85,
      "setup": 0.34,
      "near_high": 0.956,
      "extended": true,
      "pos_in_range": 1.0,
      "tightness": 0.462,
      "market_cap": 3296434447.5061035,
      "in_band": false,
      "dollar_vol": 88295799.0,
      "liquid": true,
      "short_pct": 0.1503,
      "bucket_label": "vol>=2x & +10%/5d",
      "p_up": 0.1546,
      "p_down": 0.0461,
      "why": "vol building 2.1x, +14% 5d, 15% short",
      "days_to_catalyst": null,
      "nearest_phase": null,
      "exit_by": null,
      "cat_quality": null,
      "platform": false,
      "catalysts": [
        {
          "date": "2027-01",
          "phase": "PHASE3",
          "title": "Setrusumab in Pediatric Japanese Subjects With"
        },
        {
          "date": "2027-08",
          "phase": "PHASE3",
          "title": "A Study to Determine the Effect of Triheptanoi"
        },
        {
          "date": "2027-08",
          "phase": "PHASE3",
          "title": "Follow-up Study of AAV-Mediated Gene Transfer "
        }
      ],
      "insider_buys": 0,
      "insider_usd": 0,
      "insider_recent": null,
      "conviction": "LOW",
      "stop": 25.1,
      "trail_pct": 28,
      "structure": "no near-term Phase-2 catalyst - momentum/heat play only (higher uncertainty)."
    },
    {
      "cash_runway_months": 40.9,
      "dilution_risk": false,
      "symbol": "ZBIO",
      "name": "Zenas BioPharma, Inc.",
      "price": 27.23,
      "heat": 0.84,
      "setup": 0.25,
      "near_high": 0.921,
      "extended": false,
      "pos_in_range": 0.931,
      "tightness": 0.556,
      "market_cap": 1719121826.8098335,
      "in_band": true,
      "dollar_vol": 24453365.0,
      "liquid": true,
      "short_pct": 0.2628,
      "bucket_label": "vol>=1.5x & +5%/5d",
      "p_up": 0.1034,
      "p_down": 0.0332,
      "why": "vol building 1.9x, +10% 5d, 26% short",
      "days_to_catalyst": null,
      "nearest_phase": null,
      "exit_by": null,
      "cat_quality": null,
      "platform": false,
      "catalysts": [
        {
          "date": "2030-06",
          "phase": "PHASE3",
          "title": "A Study of Orelabrutinib in Patients With Prim"
        },
        {
          "date": "2030-06",
          "phase": "PHASE3",
          "title": "A Study of Orelabrutinib in Patients With Seco"
        }
      ],
      "insider_buys": 3,
      "insider_usd": 2080000.0,
      "insider_recent": "2026-05-18",
      "conviction": "MED",
      "stop": 20.42,
      "trail_pct": 28,
      "structure": "no near-term Phase-2 catalyst - momentum/heat play only (higher uncertainty)."
    },
    {
      "cash_runway_months": 42.6,
      "dilution_risk": false,
      "symbol": "MRNA",
      "name": "Moderna, Inc.",
      "price": 79.76,
      "heat": 0.79,
      "setup": 0.24,
      "near_high": 0.98,
      "extended": true,
      "pos_in_range": 1.0,
      "tightness": 0.636,
      "market_cap": 31647672865.466896,
      "in_band": false,
      "dollar_vol": 568455994.0,
      "liquid": true,
      "short_pct": 0.18090001,
      "bucket_label": "+10%/5d",
      "p_up": 0.0911,
      "p_down": 0.0318,
      "why": "+34% 5d, 18% short",
      "days_to_catalyst": null,
      "nearest_phase": null,
      "exit_by": null,
      "cat_quality": null,
      "platform": false,
      "catalysts": [],
      "insider_buys": 0,
      "insider_usd": 0,
      "insider_recent": null,
      "conviction": "LOW",
      "stop": 59.82,
      "trail_pct": 28,
      "structure": "no near-term Phase-2 catalyst - momentum/heat play only (higher uncertainty)."
    },
    {
      "cash_runway_months": 36.2,
      "dilution_risk": false,
      "symbol": "FDMT",
      "name": "4D Molecular Therapeutics, Inc.",
      "price": 13.0,
      "heat": 0.78,
      "setup": 0.49,
      "near_high": 0.929,
      "extended": false,
      "pos_in_range": 0.939,
      "tightness": 0.497,
      "market_cap": 679591302.0,
      "in_band": true,
      "dollar_vol": 12463083.0,
      "liquid": true,
      "short_pct": 0.2859,
      "bucket_label": "+10%/5d",
      "p_up": 0.0911,
      "p_down": 0.0318,
      "why": "vol building 1.5x, coiled near range-top, +13% 5d, 29% short",
      "days_to_catalyst": null,
      "nearest_phase": null,
      "exit_by": null,
      "cat_quality": null,
      "platform": false,
      "catalysts": [
        {
          "date": "2027-03",
          "phase": "PHASE1,PHASE2",
          "title": "4D-150 in Patients With Neovascular (Wet) Age-"
        },
        {
          "date": "2027-05-26",
          "phase": "PHASE1",
          "title": "Dose Escalation Study of Intravitreal 4D-110 i"
        },
        {
          "date": "2027-06",
          "phase": "PHASE2",
          "title": "4D-710 in Adult Patients With Cystic Fibrosis"
        }
      ],
      "insider_buys": 0,
      "insider_usd": 0,
      "insider_recent": null,
      "conviction": "LOW",
      "stop": 9.75,
      "trail_pct": 28,
      "structure": "no near-term Phase-2 catalyst - momentum/heat play only (higher uncertainty)."
    },
    {
      "cash_runway_months": 55.7,
      "dilution_risk": false,
      "symbol": "BCAX",
      "name": "Bicara Therapeutics Inc.",
      "price": 29.0,
      "heat": 0.78,
      "setup": 0.28,
      "near_high": 0.97,
      "extended": true,
      "pos_in_range": 0.934,
      "tightness": 0.459,
      "market_cap": 1905412114.0,
      "in_band": true,
      "dollar_vol": 24821911.0,
      "liquid": true,
      "short_pct": 0.216,
      "bucket_label": "vol>=1.5x & +5%/5d",
      "p_up": 0.1034,
      "p_down": 0.0332,
      "why": "vol building 1.9x, +10% 5d, 22% short",
      "days_to_catalyst": null,
      "nearest_phase": null,
      "exit_by": null,
      "cat_quality": null,
      "platform": false,
      "catalysts": [
        {
          "date": "2026-12-31",
          "phase": "PHASE1",
          "title": "Study of Safety and Tolerability of BCA101 Mon"
        },
        {
          "date": "2028-04",
          "phase": "PHASE2,PHASE3",
          "title": "FORTIFI-HN01: A Study of Ficerafusp Alfa (BCA1"
        }
      ],
      "insider_buys": 0,
      "insider_usd": 0,
      "insider_recent": null,
      "conviction": "LOW",
      "stop": 21.75,
      "trail_pct": 28,
      "structure": "no near-term Phase-2 catalyst - momentum/heat play only (higher uncertainty)."
    }
  ]
}