{
  "date": "2026-07-13",
  "logged_at": "2026-07-13T09:26:43-04:00",
  "n_candidates": 52,
  "n_tradable": 51,
  "picks": [
    {
      "symbol": "APH",
      "basket": "random",
      "top_k_of": [],
      "signals": {
        "wsb_surge": null,
        "wsb_rank": null,
        "st_rank": null,
        "pm_rvol": null,
        "gap_pct": null,
        "squeeze": 2.41,
        "uoa_z": null,
        "ignition": 0,
        "penny_surge": null,
        "squeeze_sub_surge": null,
        "gtrends_spike": 0.0,
        "finra_short_ratio": 0.2567,
        "halt_reason": null,
        "realized_vol": 0.0274,
        "opt_expmove": 4.557
      },
      "combined_score": 0.1285,
      "ret_945_close": -0.861,
      "ret_1d": null,
      "ret_3d": null
    },
    {
      "symbol": "ASML",
      "basket": "gtrends",
      "top_k_of": [
        "gtrends"
      ],
      "signals": {
        "wsb_surge": 6.0,
        "wsb_rank": 27,
        "st_rank": null,
        "pm_rvol": 1.16,
        "gap_pct": null,
        "squeeze": 0.14,
        "uoa_z": null,
        "ignition": 0,
        "penny_surge": null,
        "squeeze_sub_surge": null,
        "gtrends_spike": 0.57,
        "finra_short_ratio": 0.3402,
        "halt_reason": null,
        "realized_vol": 0.0439,
        "opt_expmove": 7.298
      },
      "combined_score": 0.2608,
      "ret_945_close": -0.862,
      "ret_1d": null,
      "ret_3d": null
    },
    {
      "symbol": "ASTS",
      "basket": "wsb",
      "top_k_of": [
        "squeeze",
        "wsb"
      ],
      "signals": {
        "wsb_surge": 14.0,
        "wsb_rank": 19,
        "st_rank": null,
        "pm_rvol": 0.19,
        "gap_pct": null,
        "squeeze": 56.5,
        "uoa_z": null,
        "ignition": 0,
        "penny_surge": null,
        "squeeze_sub_surge": null,
        "gtrends_spike": 0.27,
        "finra_short_ratio": 0.5498,
        "halt_reason": null,
        "realized_vol": 0.0803,
        "opt_expmove": 8.301
      },
      "combined_score": 0.5199,
      "ret_945_close": -2.202,
      "ret_1d": null,
      "ret_3d": null
    },
    {
      "symbol": "BATL",
      "basket": "pennystocks",
      "top_k_of": [
        "pennystocks"
      ],
      "signals": {
        "wsb_surge": null,
        "wsb_rank": null,
        "st_rank": null,
        "pm_rvol": null,
        "gap_pct": null,
        "squeeze": null,
        "uoa_z": null,
        "ignition": null,
        "penny_surge": 5.0,
        "squeeze_sub_surge": null,
        "gtrends_spike": null,
        "finra_short_ratio": 0.5945,
        "halt_reason": null,
        "realized_vol": null,
        "opt_expmove": null
      },
      "combined_score": null,
      "ret_945_close": 11.765,
      "ret_1d": null,
      "ret_3d": null
    },
    {
      "symbol": "BW",
      "basket": "stocktwits",
      "top_k_of": [
        "filtered3",
        "finra_shortvol",
        "ignition",
        "stocktwits"
      ],
      "signals": {
        "wsb_surge": null,
        "wsb_rank": null,
        "st_rank": 5,
        "pm_rvol": null,
        "gap_pct": null,
        "squeeze": null,
        "uoa_z": null,
        "ignition": 2,
        "penny_surge": null,
        "squeeze_sub_surge": null,
        "gtrends_spike": 0.54,
        "finra_short_ratio": 0.7305,
        "halt_reason": null,
        "realized_vol": 0.0518,
        "opt_expmove": 9.978
      },
      "combined_score": 0.8793,
      "ret_945_close": -5.575,
      "ret_1d": null,
      "ret_3d": null
    },
    {
      "symbol": "COHR",
      "basket": "gappers",
      "top_k_of": [],
      "signals": {
        "wsb_surge": null,
        "wsb_rank": null,
        "st_rank": 12,
        "pm_rvol": 0.27,
        "gap_pct": -5.05,
        "squeeze": 7.04,
        "uoa_z": null,
        "ignition": 0,
        "penny_surge": null,
        "squeeze_sub_surge": null,
        "gtrends_spike": 0.34,
        "finra_short_ratio": 0.4059,
        "halt_reason": null,
        "realized_vol": 0.0555,
        "opt_expmove": 8.905
      },
      "combined_score": 0.408,
      "ret_945_close": -1.957,
      "ret_1d": null,
      "ret_3d": null
    },
    {
      "symbol": "CRMD",
      "basket": "gappers",
      "top_k_of": [],
      "signals": {
        "wsb_surge": null,
        "wsb_rank": null,
        "st_rank": 7,
        "pm_rvol": null,
        "gap_pct": -3.17,
        "squeeze": null,
        "uoa_z": null,
        "ignition": 0,
        "penny_surge": null,
        "squeeze_sub_surge": null,
        "gtrends_spike": 0.0,
        "finra_short_ratio": 0.5552,
        "halt_reason": null,
        "realized_vol": 0.0318,
        "opt_expmove": 7.091
      },
      "combined_score": 0.2529,
      "ret_945_close": -0.12,
      "ret_1d": null,
      "ret_3d": null
    },
    {
      "symbol": "DRAM",
      "basket": "gappers",
      "top_k_of": [],
      "signals": {
        "wsb_surge": null,
        "wsb_rank": null,
        "st_rank": 11,
        "pm_rvol": 0.14,
        "gap_pct": -10.77,
        "squeeze": null,
        "uoa_z": null,
        "ignition": 0,
        "penny_surge": null,
        "squeeze_sub_surge": null,
        "gtrends_spike": 0.38,
        "finra_short_ratio": 0.4619,
        "halt_reason": null,
        "realized_vol": 0.0723,
        "opt_expmove": 8.564
      },
      "combined_score": 0.4183,
      "ret_945_close": 0.828,
      "ret_1d": null,
      "ret_3d": null
    },
    {
      "symbol": "DUOL",
      "basket": "random",
      "top_k_of": [],
      "signals": {
        "wsb_surge": null,
        "wsb_rank": null,
        "st_rank": null,
        "pm_rvol": null,
        "gap_pct": null,
        "squeeze": 96.82,
        "uoa_z": null,
        "ignition": 0,
        "penny_surge": null,
        "squeeze_sub_surge": null,
        "gtrends_spike": 0.68,
        "finra_short_ratio": 0.6662,
        "halt_reason": null,
        "realized_vol": 0.0351,
        "opt_expmove": 5.896
      },
      "combined_score": 0.4714,
      "ret_945_close": 3.408,
      "ret_1d": null,
      "ret_3d": null
    },
    {
      "symbol": "EMR",
      "basket": "random",
      "top_k_of": [],
      "signals": {
        "wsb_surge": null,
        "wsb_rank": null,
        "st_rank": null,
        "pm_rvol": null,
        "gap_pct": null,
        "squeeze": 8.49,
        "uoa_z": null,
        "ignition": 0,
        "penny_surge": null,
        "squeeze_sub_surge": null,
        "gtrends_spike": 0.57,
        "finra_short_ratio": 0.547,
        "halt_reason": null,
        "realized_vol": 0.0194,
        "opt_expmove": 2.548
      },
      "combined_score": 0.3286,
      "ret_945_close": -2.28,
      "ret_1d": null,
      "ret_3d": null
    },
    {
      "symbol": "ES",
      "basket": "wsb",
      "top_k_of": [
        "finra_shortvol",
        "wsb"
      ],
      "signals": {
        "wsb_surge": 19.0,
        "wsb_rank": 11,
        "st_rank": null,
        "pm_rvol": null,
        "gap_pct": null,
        "squeeze": null,
        "uoa_z": null,
        "ignition": 1,
        "penny_surge": null,
        "squeeze_sub_surge": null,
        "gtrends_spike": 0.51,
        "finra_short_ratio": 0.7001,
        "halt_reason": null,
        "realized_vol": 0.0128,
        "opt_expmove": 1.559
      },
      "combined_score": 0.7938,
      "ret_945_close": -0.991,
      "ret_1d": null,
      "ret_3d": null
    },
    {
      "symbol": "HBM",
      "basket": "wsb",
      "top_k_of": [
        "wsb"
      ],
      "signals": {
        "wsb_surge": 17.0,
        "wsb_rank": 15,
        "st_rank": null,
        "pm_rvol": null,
        "gap_pct": null,
        "squeeze": null,
        "uoa_z": null,
        "ignition": 0,
        "penny_surge": null,
        "squeeze_sub_surge": null,
        "gtrends_spike": 0.33,
        "finra_short_ratio": 0.5549,
        "halt_reason": null,
        "realized_vol": 0.0457,
        "opt_expmove": 6.255
      },
      "combined_score": 0.4933,
      "ret_945_close": -2.498,
      "ret_1d": null,
      "ret_3d": null
    },
    {
      "symbol": "HOOD",
      "basket": "wsb",
      "top_k_of": [
        "finra_shortvol",
        "wsb"
      ],
      "signals": {
        "wsb_surge": 13.0,
        "wsb_rank": 20,
        "st_rank": null,
        "pm_rvol": 0.99,
        "gap_pct": null,
        "squeeze": 5.34,
        "uoa_z": null,
        "ignition": 0,
        "penny_surge": null,
        "squeeze_sub_surge": null,
        "gtrends_spike": 0.39,
        "finra_short_ratio": 0.6446,
        "halt_reason": null,
        "realized_vol": 0.0423,
        "opt_expmove": 5.838
      },
      "combined_score": 0.4782,
      "ret_945_close": -0.353,
      "ret_1d": null,
      "ret_3d": null
    },
    {
      "symbol": "JPM",
      "basket": "random",
      "top_k_of": [],
      "signals": {
        "wsb_surge": null,
        "wsb_rank": null,
        "st_rank": null,
        "pm_rvol": 2.2,
        "gap_pct": null,
        "squeeze": 2.77,
        "uoa_z": null,
        "ignition": 1,
        "penny_surge": null,
        "squeeze_sub_surge": null,
        "gtrends_spike": 0.37,
        "finra_short_ratio": 0.4479,
        "halt_reason": null,
        "realized_vol": 0.0155,
        "opt_expmove": 3.223
      },
      "combined_score": 0.6487,
      "ret_945_close": 0.024,
      "ret_1d": null,
      "ret_3d": null
    },
    {
      "symbol": "KORU",
      "basket": "wsb",
      "top_k_of": [
        "gtrends",
        "options",
        "wsb"
      ],
      "signals": {
        "wsb_surge": 14.0,
        "wsb_rank": 18,
        "st_rank": 6,
        "pm_rvol": 0.68,
        "gap_pct": -23.92,
        "squeeze": null,
        "uoa_z": null,
        "ignition": 0,
        "penny_surge": null,
        "squeeze_sub_surge": null,
        "gtrends_spike": 0.65,
        "finra_short_ratio": 0.5662,
        "halt_reason": null,
        "realized_vol": 0.1498,
        "opt_expmove": 19.02
      },
      "combined_score": 0.5992,
      "ret_945_close": -2.169,
      "ret_1d": null,
      "ret_3d": null
    },
    {
      "symbol": "MCK",
      "basket": "random",
      "top_k_of": [],
      "signals": {
        "wsb_surge": null,
        "wsb_rank": null,
        "st_rank": null,
        "pm_rvol": null,
        "gap_pct": null,
        "squeeze": 12.95,
        "uoa_z": null,
        "ignition": 0,
        "penny_surge": null,
        "squeeze_sub_surge": null,
        "gtrends_spike": 0.0,
        "finra_short_ratio": 0.3775,
        "halt_reason": null,
        "realized_vol": 0.017,
        "opt_expmove": 2.455
      },
      "combined_score": 0.4,
      "ret_945_close": -0.581,
      "ret_1d": null,
      "ret_3d": null
    },
    {
      "symbol": "MDGL",
      "basket": "gappers",
      "top_k_of": [],
      "signals": {
        "wsb_surge": null,
        "wsb_rank": null,
        "st_rank": 30,
        "pm_rvol": null,
        "gap_pct": -4.33,
        "squeeze": null,
        "uoa_z": null,
        "ignition": 0,
        "penny_surge": null,
        "squeeze_sub_surge": null,
        "gtrends_spike": 0.0,
        "finra_short_ratio": 0.4502,
        "halt_reason": null,
        "realized_vol": 0.0213,
        "opt_expmove": 4.242
      },
      "combined_score": 0.1111,
      "ret_945_close": -0.253,
      "ret_1d": null,
      "ret_3d": null
    },
    {
      "symbol": "MSFT",
      "basket": "wsb",
      "top_k_of": [
        "pennystocks",
        "wsb"
      ],
      "signals": {
        "wsb_surge": 4.0,
        "wsb_rank": 3,
        "st_rank": null,
        "pm_rvol": 0.12,
        "gap_pct": null,
        "squeeze": 2.21,
        "uoa_z": null,
        "ignition": 0,
        "penny_surge": 1.0,
        "squeeze_sub_surge": null,
        "gtrends_spike": 0.34,
        "finra_short_ratio": 0.3879,
        "halt_reason": null,
        "realized_vol": 0.0227,
        "opt_expmove": 3.348
      },
      "combined_score": 0.3151,
      "ret_945_close": 0.383,
      "ret_1d": null,
      "ret_3d": null
    },
    {
      "symbol": "MU",
      "basket": "wsb",
      "top_k_of": [
        "wsb"
      ],
      "signals": {
        "wsb_surge": 10.4,
        "wsb_rank": 1,
        "st_rank": null,
        "pm_rvol": 0.8,
        "gap_pct": null,
        "squeeze": 1.55,
        "uoa_z": null,
        "ignition": 0,
        "penny_surge": null,
        "squeeze_sub_surge": null,
        "gtrends_spike": 0.37,
        "finra_short_ratio": 0.3272,
        "halt_reason": null,
        "realized_vol": 0.0734,
        "opt_expmove": 9.963
      },
      "combined_score": 0.472,
      "ret_945_close": 2.985,
      "ret_1d": null,
      "ret_3d": null
    },
    {
      "symbol": "NBIS",
      "basket": "options",
      "top_k_of": [
        "options",
        "squeeze"
      ],
      "signals": {
        "wsb_surge": 13.0,
        "wsb_rank": 23,
        "st_rank": null,
        "pm_rvol": 0.25,
        "gap_pct": null,
        "squeeze": 98.73,
        "uoa_z": null,
        "ignition": 0,
        "penny_surge": null,
        "squeeze_sub_surge": null,
        "gtrends_spike": 0.37,
        "finra_short_ratio": 0.5953,
        "halt_reason": null,
        "realized_vol": 0.0684,
        "opt_expmove": 11.774
      },
      "combined_score": 0.4888,
      "ret_945_close": 0.933,
      "ret_1d": null,
      "ret_3d": null
    },
    {
      "symbol": "NEM",
      "basket": "random",
      "top_k_of": [],
      "signals": {
        "wsb_surge": null,
        "wsb_rank": null,
        "st_rank": null,
        "pm_rvol": null,
        "gap_pct": null,
        "squeeze": 4.43,
        "uoa_z": null,
        "ignition": 0,
        "penny_surge": null,
        "squeeze_sub_surge": null,
        "gtrends_spike": 0.0,
        "finra_short_ratio": 0.4902,
        "halt_reason": null,
        "realized_vol": 0.0279,
        "opt_expmove": 4.161
      },
      "combined_score": 0.2429,
      "ret_945_close": -0.358,
      "ret_1d": null,
      "ret_3d": null
    },
    {
      "symbol": "O",
      "basket": "random",
      "top_k_of": [],
      "signals": {
        "wsb_surge": null,
        "wsb_rank": null,
        "st_rank": null,
        "pm_rvol": null,
        "gap_pct": null,
        "squeeze": 34.74,
        "uoa_z": null,
        "ignition": 0,
        "penny_surge": null,
        "squeeze_sub_surge": null,
        "gtrends_spike": 0.49,
        "finra_short_ratio": 0.5288,
        "halt_reason": null,
        "realized_vol": 0.0129,
        "opt_expmove": 1.871
      },
      "combined_score": 0.4429,
      "ret_945_close": 0.336,
      "ret_1d": null,
      "ret_3d": null
    },
    {
      "symbol": "OTLK",
      "basket": "pennystocks",
      "top_k_of": [
        "pennystocks"
      ],
      "signals": {
        "wsb_surge": null,
        "wsb_rank": null,
        "st_rank": null,
        "pm_rvol": null,
        "gap_pct": null,
        "squeeze": null,
        "uoa_z": null,
        "ignition": null,
        "penny_surge": 3.0,
        "squeeze_sub_surge": null,
        "gtrends_spike": null,
        "finra_short_ratio": 0.5657,
        "halt_reason": null,
        "realized_vol": null,
        "opt_expmove": null
      },
      "combined_score": null,
      "ret_945_close": -1.27,
      "ret_1d": null,
      "ret_3d": null
    },
    {
      "symbol": "PLTR",
      "basket": "random",
      "top_k_of": [],
      "signals": {
        "wsb_surge": null,
        "wsb_rank": null,
        "st_rank": null,
        "pm_rvol": 0.15,
        "gap_pct": null,
        "squeeze": 8.34,
        "uoa_z": null,
        "ignition": 0,
        "penny_surge": null,
        "squeeze_sub_surge": null,
        "gtrends_spike": 0.37,
        "finra_short_ratio": 0.6106,
        "halt_reason": null,
        "realized_vol": 0.0357,
        "opt_expmove": 4.49
      },
      "combined_score": 0.3357,
      "ret_945_close": 0.998,
      "ret_1d": null,
      "ret_3d": null
    },
    {
      "symbol": "PSKY",
      "basket": "gtrends",
      "top_k_of": [
        "finra_shortvol",
        "gtrends"
      ],
      "signals": {
        "wsb_surge": null,
        "wsb_rank": null,
        "st_rank": 26,
        "pm_rvol": null,
        "gap_pct": null,
        "squeeze": null,
        "uoa_z": null,
        "ignition": 0,
        "penny_surge": null,
        "squeeze_sub_surge": null,
        "gtrends_spike": 0.57,
        "finra_short_ratio": 0.6629,
        "halt_reason": null,
        "realized_vol": 0.0204,
        "opt_expmove": 5.151
      },
      "combined_score": 0.0689,
      "ret_945_close": -0.572,
      "ret_1d": null,
      "ret_3d": null
    },
    {
      "symbol": "QQQ",
      "basket": "wsb",
      "top_k_of": [
        "finra_shortvol",
        "ignition",
        "wsb"
      ],
      "signals": {
        "wsb_surge": 3.8,
        "wsb_rank": 6,
        "st_rank": null,
        "pm_rvol": 0.27,
        "gap_pct": null,
        "squeeze": null,
        "uoa_z": null,
        "ignition": 2,
        "penny_surge": null,
        "squeeze_sub_surge": null,
        "gtrends_spike": 0.37,
        "finra_short_ratio": 0.7382,
        "halt_reason": null,
        "realized_vol": 0.0184,
        "opt_expmove": 1.937
      },
      "combined_score": 0.5876,
      "ret_945_close": -0.388,
      "ret_1d": null,
      "ret_3d": null
    },
    {
      "symbol": "QTTB",
      "basket": "stocktwits",
      "top_k_of": [
        "filtered3",
        "gtrends",
        "stocktwits"
      ],
      "signals": {
        "wsb_surge": null,
        "wsb_rank": null,
        "st_rank": 2,
        "pm_rvol": null,
        "gap_pct": 47.69,
        "squeeze": null,
        "uoa_z": null,
        "ignition": 0,
        "penny_surge": null,
        "squeeze_sub_surge": null,
        "gtrends_spike": 1.0,
        "finra_short_ratio": 0.2405,
        "halt_reason": null,
        "realized_vol": 0.0625,
        "opt_expmove": null
      },
      "combined_score": 0.6159,
      "ret_945_close": 16.253,
      "ret_1d": null,
      "ret_3d": null
    },
    {
      "symbol": "RCAT",
      "basket": "stocktwits",
      "top_k_of": [
        "stocktwits"
      ],
      "signals": {
        "wsb_surge": null,
        "wsb_rank": null,
        "st_rank": 4,
        "pm_rvol": null,
        "gap_pct": -4.03,
        "squeeze": null,
        "uoa_z": null,
        "ignition": 0,
        "penny_surge": null,
        "squeeze_sub_surge": null,
        "gtrends_spike": 0.48,
        "finra_short_ratio": 0.6135,
        "halt_reason": null,
        "realized_vol": 0.0582,
        "opt_expmove": 9.334
      },
      "combined_score": 0.3707,
      "ret_945_close": -0.532,
      "ret_1d": null,
      "ret_3d": null
    },
    {
      "symbol": "SLNH",
      "basket": "pennystocks",
      "top_k_of": [
        "pennystocks"
      ],
      "signals": {
        "wsb_surge": null,
        "wsb_rank": null,
        "st_rank": null,
        "pm_rvol": null,
        "gap_pct": null,
        "squeeze": null,
        "uoa_z": null,
        "ignition": null,
        "penny_surge": 3.0,
        "squeeze_sub_surge": null,
        "gtrends_spike": null,
        "finra_short_ratio": 0.5592,
        "halt_reason": null,
        "realized_vol": null,
        "opt_expmove": null
      },
      "combined_score": null,
      "ret_945_close": -7.407,
      "ret_1d": null,
      "ret_3d": null
    },
    {
      "symbol": "SNDK",
      "basket": "wsb",
      "top_k_of": [
        "filtered3",
        "ignition",
        "pm_rvol",
        "wsb"
      ],
      "signals": {
        "wsb_surge": 6.4,
        "wsb_rank": 5,
        "st_rank": null,
        "pm_rvol": 1.81,
        "gap_pct": null,
        "squeeze": null,
        "uoa_z": null,
        "ignition": 2,
        "penny_surge": null,
        "squeeze_sub_surge": null,
        "gtrends_spike": 0.39,
        "finra_short_ratio": 0.4829,
        "halt_reason": null,
        "realized_vol": 0.095,
        "opt_expmove": 11.033
      },
      "combined_score": 0.7622,
      "ret_945_close": -2.285,
      "ret_1d": null,
      "ret_3d": null
    },
    {
      "symbol": "SOFI",
      "basket": "stocktwits",
      "top_k_of": [
        "pm_rvol",
        "squeeze",
        "stocktwits"
      ],
      "signals": {
        "wsb_surge": 13.0,
        "wsb_rank": 21,
        "st_rank": 1,
        "pm_rvol": 1.91,
        "gap_pct": 3.55,
        "squeeze": 33.46,
        "uoa_z": null,
        "ignition": 0,
        "penny_surge": null,
        "squeeze_sub_surge": null,
        "gtrends_spike": 0.4,
        "finra_short_ratio": 0.4904,
        "halt_reason": null,
        "realized_vol": 0.0262,
        "opt_expmove": 5.287
      },
      "combined_score": 0.562,
      "ret_945_close": -3.388,
      "ret_1d": null,
      "ret_3d": null
    },
    {
      "symbol": "SOXL",
      "basket": "options",
      "top_k_of": [
        "options"
      ],
      "signals": {
        "wsb_surge": 2.8,
        "wsb_rank": 29,
        "st_rank": null,
        "pm_rvol": 0.79,
        "gap_pct": null,
        "squeeze": null,
        "uoa_z": null,
        "ignition": 1,
        "penny_surge": null,
        "squeeze_sub_surge": null,
        "gtrends_spike": 0.37,
        "finra_short_ratio": 0.5904,
        "halt_reason": null,
        "realized_vol": 0.137,
        "opt_expmove": 15.491
      },
      "combined_score": 0.3843,
      "ret_945_close": -0.765,
      "ret_1d": null,
      "ret_3d": null
    },
    {
      "symbol": "SPCH",
      "basket": "gappers",
      "top_k_of": [
        "options"
      ],
      "signals": {
        "wsb_surge": null,
        "wsb_rank": null,
        "st_rank": 13,
        "pm_rvol": 0.0,
        "gap_pct": -7.59,
        "squeeze": null,
        "uoa_z": null,
        "ignition": null,
        "penny_surge": null,
        "squeeze_sub_surge": null,
        "gtrends_spike": 0.0,
        "finra_short_ratio": 0.45,
        "halt_reason": null,
        "realized_vol": null,
        "opt_expmove": 11.652
      },
      "combined_score": 0.3898,
      "ret_945_close": -1.976,
      "ret_1d": null,
      "ret_3d": null
    },
    {
      "symbol": "SPGI",
      "basket": "random",
      "top_k_of": [],
      "signals": {
        "wsb_surge": null,
        "wsb_rank": null,
        "st_rank": null,
        "pm_rvol": null,
        "gap_pct": null,
        "squeeze": 1.65,
        "uoa_z": null,
        "ignition": 0,
        "penny_surge": null,
        "squeeze_sub_surge": null,
        "gtrends_spike": 0.48,
        "finra_short_ratio": 0.521,
        "halt_reason": null,
        "realized_vol": 0.0226,
        "opt_expmove": 1.86
      },
      "combined_score": 0.0571,
      "ret_945_close": 0.064,
      "ret_1d": null,
      "ret_3d": null
    },
    {
      "symbol": "SPY",
      "basket": "wsb",
      "top_k_of": [
        "wsb"
      ],
      "signals": {
        "wsb_surge": 3.3,
        "wsb_rank": 2,
        "st_rank": null,
        "pm_rvol": 1.27,
        "gap_pct": null,
        "squeeze": null,
        "uoa_z": null,
        "ignition": 1,
        "penny_surge": null,
        "squeeze_sub_surge": null,
        "gtrends_spike": 0.35,
        "finra_short_ratio": 0.6278,
        "halt_reason": null,
        "realized_vol": 0.0088,
        "opt_expmove": 0.994
      },
      "combined_score": 0.6381,
      "ret_945_close": -0.486,
      "ret_1d": null,
      "ret_3d": null
    },
    {
      "symbol": "SSPC",
      "basket": "gappers",
      "top_k_of": [
        "options"
      ],
      "signals": {
        "wsb_surge": null,
        "wsb_rank": null,
        "st_rank": 15,
        "pm_rvol": 0.27,
        "gap_pct": 11.28,
        "squeeze": null,
        "uoa_z": null,
        "ignition": null,
        "penny_surge": null,
        "squeeze_sub_surge": null,
        "gtrends_spike": 0.0,
        "finra_short_ratio": 0.4385,
        "halt_reason": null,
        "realized_vol": null,
        "opt_expmove": 11.491
      },
      "combined_score": 0.5756,
      "ret_945_close": 1.869,
      "ret_1d": null,
      "ret_3d": null
    },
    {
      "symbol": "STLA",
      "basket": "gappers",
      "top_k_of": [
        "pm_rvol"
      ],
      "signals": {
        "wsb_surge": null,
        "wsb_rank": null,
        "st_rank": 10,
        "pm_rvol": 2.83,
        "gap_pct": 5.43,
        "squeeze": null,
        "uoa_z": null,
        "ignition": 1,
        "penny_surge": null,
        "squeeze_sub_surge": null,
        "gtrends_spike": 0.33,
        "finra_short_ratio": 0.4995,
        "halt_reason": null,
        "realized_vol": 0.0286,
        "opt_expmove": 5.511
      },
      "combined_score": 0.7192,
      "ret_945_close": -2.535,
      "ret_1d": null,
      "ret_3d": null
    },
    {
      "symbol": "TSM",
      "basket": "stocktwits",
      "top_k_of": [
        "pm_rvol",
        "stocktwits"
      ],
      "signals": {
        "wsb_surge": 6.0,
        "wsb_rank": 25,
        "st_rank": 3,
        "pm_rvol": 2.07,
        "gap_pct": null,
        "squeeze": 1.09,
        "uoa_z": null,
        "ignition": 0,
        "penny_surge": null,
        "squeeze_sub_surge": null,
        "gtrends_spike": 0.53,
        "finra_short_ratio": 0.3993,
        "halt_reason": null,
        "realized_vol": 0.037,
        "opt_expmove": 5.576
      },
      "combined_score": 0.4028,
      "ret_945_close": -1.27,
      "ret_1d": null,
      "ret_3d": null
    },
    {
      "symbol": "UVXY",
      "basket": "gappers",
      "top_k_of": [
        "gtrends"
      ],
      "signals": {
        "wsb_surge": null,
        "wsb_rank": null,
        "st_rank": 20,
        "pm_rvol": 0.0,
        "gap_pct": -3.46,
        "squeeze": null,
        "uoa_z": null,
        "ignition": 1,
        "penny_surge": null,
        "squeeze_sub_surge": null,
        "gtrends_spike": 1.0,
        "finra_short_ratio": 0.6161,
        "halt_reason": null,
        "realized_vol": 0.0428,
        "opt_expmove": 5.479
      },
      "combined_score": 0.2924,
      "ret_945_close": 2.93,
      "ret_1d": null,
      "ret_3d": null
    },
    {
      "symbol": "WBD",
      "basket": "random",
      "top_k_of": [],
      "signals": {
        "wsb_surge": null,
        "wsb_rank": null,
        "st_rank": 14,
        "pm_rvol": 0.0,
        "gap_pct": null,
        "squeeze": 9.09,
        "uoa_z": null,
        "ignition": 0,
        "penny_surge": null,
        "squeeze_sub_surge": null,
        "gtrends_spike": 0.47,
        "finra_short_ratio": 0.1634,
        "halt_reason": null,
        "realized_vol": 0.013,
        "opt_expmove": 3.938
      },
      "combined_score": 0.3094,
      "ret_945_close": 1.047,
      "ret_1d": null,
      "ret_3d": null
    }
  ],
  "scored_at": "2026-07-13T16:10:04-04:00"
}